setup.py
invoicing/__init__.py
invoicing/invoice.py
pdf_invoice.egg-info/PKG-INFO
pdf_invoice.egg-info/SOURCES.txt
pdf_invoice.egg-info/dependency_links.txt
pdf_invoice.egg-info/requires.txt
pdf_invoice.egg-info/top_level.txt